Workbook

Sheet Diagrama ER (corregido)

Sheet Tipos de Dato
A1: Tipos de Datos - Tabla Comparativa
A2: # | B2: Tipo de Dato Genérico | C2: Descripción | D2: En PosgreSQL | E2: En MySQL | F2: En MS SQL Server
D3: Versión: 18.1 | E3: Versión: 9.6.0 | F3: Versión:
A4: 1 | B4: AUTOINCREMENTABLE | C4: Genera automáticamente un valor numérico secuencial único para cada nuevo registro. | D4: SERIAL | E4: INT AUTO_INCREMENT | F4: INT IDENTITY(1,1)
A5: =A4+1 -> 2 | B5: UUID | C5: Identificador universal único de 128 bits, ideal para sistemas distribuidos. | D5: UUID | E5: CHAR/NUMERIC | F5: UNIQUEIDENTIFIER
A6: =A5+1 -> 3 | B6: ENTERO | C6: Almacena números numéricos exactos sin decimales (positivos o negativos). | D6: INT/INTEGER | E6: INT | F6: INT
A7: =A6+1 -> 4 | B7: DECIMAL | C7: Almacena números con precisión exacta, ideal para cálculos financieros y monedas | D7: DECIMAL/NUMERIC | E7: DECIMAL/NUMERIC | F7: DECIMAL(p,s) / NUMERIC(p,s)
A8: =A7+1 -> 5 | B8: LÓGICO | C8: Representa valores de verdad, generalmente True o False | D8: BOOLEAN | E8: BOOLEAN | F8: BIT
A9: =A8+1 -> 6 | B9: TEXTO | C9: Cadena de caracteres de longitud variable para almacenar grandes volúmenes de palabras | D9: TEXT | E9: TEXT | F9: NVARCHAR(MAX) / VARCHAR(MAX)
A10: =A9+1 -> 7 | B10: CARACTER | C10: Almacena una cadena de longitud fija se rellena con espacios si el texto es más corto | D10: CHAR(n) | E10: CHAR(n) | F10: CHAR(n) / NCHAR(n)
A11: =A10+1 -> 8 | B11: FECHA | C11: Almacena únicamente el calendario año, mes, día sin información de la hora. | D11: DATE | E11: DATE | F11: DATE
A12: =A11+1 -> 9 | B12: FECHA_HORA | C12: Combina fecha y hora del día en un solo campo para registrar momentos exactos. | D12: TIMESTAMP | E12: DATETIME | F12: DATETIME2
A13: =A12+1 -> 10 | B13: HORA | C13: Almacena exclusivamente el tiempo horas, minutos, segundos de un evento. | D13: TIME | E13: TIME | F13: TIME
A14: =A13+1 -> 11 | B14: URL | C14: Cadena de texto diseñada para almacenar direcciones de recursos web o enlaces. | D14: =D16 -> VARCHAR(n) | E14: VARCHAR(n) | F14: VARCHAR(n) / NVARCHAR(n)
A15: =A14+1 -> 12 | B15: ENUM | C15: Lista estática de valores permitidos; el campo solo puede tomar un valor de esa lista. | D15: CREATE TYPE ... AS ENUM | E15: ENUM('valor1', 'valor2', ...) | F15: CHECK (col IN ('v1','v2',…))
A16: =A15+1 -> 13 | B16: TEXTO_CORTO | C16: Cadena de longitud variable con un límite máximo definido como nombres o correos | D16: VARCHAR(n) | E16: VARCHAR (n) | F16: VARCHAR(n)
A17: =A16+1 -> 14 | B17: BINARIO | C17: Almacena datos en formato de bytes, como archivos, documentos o ejecutables. | D17: BYTEA | E17: BLOB | F17: VARBINARY(MAX)
A18: =A17+1 -> 15 | B18: JSON | C18: Almacena datos estructurados en formato de texto siguiendo el estándar JSON. | D18: JSON | E18: JSON | F18: NVARCHAR(MAX)JSON_VALUE / OPENJSON
A19: =A18+1 -> 16 | B19: JSONB | C19: Versión binaria y optimizada de JSON que permite una búsqueda e indexación más rápida. | D19: JSONB | E19: NO EXISTE | F19: NVARCHAR(MAX)
A20: =A19+1 -> 17 | B20: IMAGEN | C20: Almacena datos binarios específicos para archivos gráficos o rutas de acceso a los mismos. | D20: BYTEA O TEXT | E20: BLOB / LONGBLOB | F20: VARBINARY(MAX)
A21: =A20+1 -> 18 | B21: AUDIO | C21: Almacena archivos de sonido en formato binario o referencias a su ubicación. | D21: BYTEA O TEXT | E21: BLOB / LONGBLOB | F21: VARBINARY(MAX)

Sheet Invetario de Tablas
A1: Modelo Lógico - Tablas resultantes del Diccionario Genérico (corregido)
A2: INVENTARIO DE TABLAS Este inventario es el mismo para los 3 SGBDs: PostgreSQL, MySQL y MS SQL Server. Todos los diccionarios deben tomar la misma cantidad y los mismos nombres de esta tablas
A3: # | B3: Tabla | C3: Descripción Tabla | D3: Observaciones
A4: 1 | B4: organizacion | C4: Contiene los datos de cooperativas, asociaciones apícolas o entidades relacionadas con el sector.
A5: =A4+1 -> 2 | B5: usuarios | C5: Almacena la información de las personas registradas en la plataforma como productores, consumidores, administradores o entidades regulatorias.
A6: =A5+1 -> 3 | B6: apiario | C6: Registra los apiarios donde se encuentran las colmenas, incluyendo ubicación geográfica y productor responsable.
A7: =A6+1 -> 4 | B7: colmena | C7: Almacena información individual de cada colmena dentro de un apiario.
A8: =A7+1 -> 5 | B8: sensor | C8: Contiene la información de los sensores IoT instalados en los apiarios para monitoreo.
A9: =A8+1 -> 6 | B9: lectura_sensor | C9: Registra los datos capturados por los sensores IoT en diferentes momentos.
A10: =A9+1 -> 7 | B10: control | C10: Guarda el historial de revisiones sanitarias de las colmenas.
A11: =A10+1 -> 8 | B11: cosecha | C11: Registra las cosechas realizadas en los apiarios.
A12: =A11+1 -> 9 | B12: lote | C12: Registra los lotes de productos apícolas derivados de una cosecha específica.
A13: =A12+1 -> 10 | B13: inventario | C13: Registra el control de existencias de los lotes de productos apícolas.
A14: =A13+1 -> 11 | B14: publicacion | C14: Permite a los productores publicar lotes disponibles para venta en el marketplace.
A15: =A14+1 -> 12 | B15: pedido | C15: Almacena los pedidos realizados por consumidores o cooperativas.
A16: =A15+1 -> 13 | B16: pedido_lote | C16: Tabla intermedia M:N que relaciona pedidos con los lotes incluidos.
... A21: =A20+1 -> 18 | B21: obligacion | C21: Registra los créditos y subsidios asociados a usuarios y organizaciones financieras.

Sheet Diccionario Datos - PostgreSQL
A1: PostgreSQL - Tablas en Detalle
A3: ='Invetario de Tablas'!A4 -> 1 | B3: Tabla | C3: organizacion | G3: Descripción Tabla | K3: Contiene los datos de cooperativas, asociaciones apícolas o entidades relacionadas con el sector. | X3: Versión | Y3: 1
A4: # | B4: Campo | C4: Descripción Campo | G4: Tipo Dato - PostgreSQL | K4: Tamaño | O4: Nulo | R4: PK | T4: FK | V4: UK | X4: Nota/Comentarios
A5: 1 | B5: id_organizacion | C5: Identificador unico de las organizaciones | G5: SERIAL | R5: S
A6: 2 | B6: nombre | C6: Nombre de la organizacion | G6: VARCHAR | K6: 100 | O6: NO
A7: 3 | B7: tipo | C7: Tipo de la organizacion | G7: VARCHAR | K7: 50 | O7: NO
A8: 4 | B8: direccion | C8: direccion de la organizacion | G8: VARCHAR | K8: 150
A9: 5 | B9: telefono | C9: Telefono de contacto de la organizacion | G9: VARCHAR | K9: 25
A10: 6 | B10: nit | C10: Numero de identificacion tributaria | G10: VARCHAR | K10: 20 | O10: NO | V10: S
A12: ='Invetario de Tablas'!A5 -> 2 | B12: Tabla | C12: usuarios | G12: Descripción Tabla | K12: Almacena la información de las personas registradas en la plataforma como productores, consumidores, administradores o entidades regulatorias. | X12: Versión | Y12: 1
A13: # | B13: Campo | C13: Descripción Campo | G13: Tipo Dato - PostgreSQL | K13: Tamaño | O13: Nulo | R13: PK | T13: FK | V13: UK | X13: Nota/Comentarios
A14: 1 | B14: id_usuario | C14: identificador unico del usuario | G14: SERIAL | R14: S
A15: 2 | B15: nombre | C15: Nombre del usuario | G15: VARCHAR | K15: 100 | O15: NO
A16: 3 | B16: email | C16: Correo electronico del usuario | G16: VARCHAR | K16: 130 | O16: NO | V16: S
A17: 4 | B17: contrasena | C17: Contraseña del usuario | G17: VARCHAR | K17: 260 | O17: NO | X17: Se omite la 'ñ' por buenas prácticas y compatibilidad de codificación en BD.
A18: 5 | B18: telefono | C18: Telefono de contacto | G18: VARCHAR | K18: 25
A19: 6 | B19: tipo_usuario | C19: Rol del usuario | G19: VARCHAR | K19: 30 | O19: NO | X19: Rol del usuario ej. productor, consumidor, o administrador
A20: 7 | B20: fecha_registro | C20: Fecha del registro | G20: DATE | O20: NO
A21: 8 | B21: id_organizacion | C21: identificador de la organiazicion a la que pertenece | G21: INT | O21: NO | T21: S | X21: Referencia a la tabla organizacion
A23: ='Invetario de Tablas'!A6 -> 3 | B23: Tabla | C23: ='Invetario de Tablas'!B6 -> apiario | G23: Descripción Tabla | K23: ='Invetario de Tablas'!C6 -> Registra los apiarios donde se encuentran las colmenas, incluyendo ubicación geográfica y productor responsable. | X23: Versión | Y23: 1
A24: # | B24: Campo | C24: Descripción Campo | G24: Tipo Dato - PostgreSQL | K24: Tamaño | O24: Nulo | R24: PK | T24: FK | V24: UK | X24: Nota/Comentarios
A25: 1 | B25: id_apiario | C25: Identificador unico del apiario | G25: SERIAL | R25: S
A26: 2 | B26: nombre_apiario | C26: Nombre del apiario | G26: VARCHAR | K26: 100 | O26: NO
A27: 3 | B27: ubicacion | C27: Ubicacion del apiario | G27: JSONB | O27: NO | X27: Se definio como jsonb
A28: 4 | B28: id_usuario | C28: Identificador unico del usuario | G28: INT | O28: NO | T28: S
A29: 5 | B29: descripcion | C29: Descripcion de apiario | G29: TEXT
A31: ='Invetario de Tablas'!A7 -> 4 | B31: Tabla | C31: ='Invetario de Tablas'!B7 -> colmena | G31: Descripción Tabla | K31: ='Invetario de Tablas'!C7 -> Almacena información individual de cada colmena dentro de un apiario. | X31: Versión | Y31: 1
A32: # | B32: Campo | C32: Descripción Campo | G32: Tipo Dato - PostgreSQL | K32: Tamaño | O32: Nulo | R32: PK | T32: FK | V32: UK | X32: Nota/Comentarios
A33: 1 | B33: id_colmena | C33: Identificador unico de la colmena | G33: SERIAL | R33: S
A34: 2 | B34: id_apiario | C34: Identificador del apiario | G34: INT | O34: NO | T34: S
A35: 3 | B35: codigo_colmena | C35: Identificador fisico del apiario | G35: VARCHAR | K35: 50 | O35: NO | V35: S
A36: 4 | B36: estado | C36: Estado en el que se encuentra la colmena | G36: VARCHAR | K36: 50 | O36: NO
A37: 5 | B37: tipo_abeja | C37: Tipo de abeja de la colmena | G37: VARCHAR | K37: 50 | O37: NO
A38: 6 | B38: fecha_instalacion | C38: Fecha de instalacion de la colmena | G38: DATE | O38: NO
A40: ='Invetario de Tablas'!A8 -> 5 | B40: Tabla | C40: ='Invetario de Tablas'!B8 -> sensor | G40: Descripción Tabla | K40: ='Invetario de Tablas'!C8 -> Contiene la información de los sensores IoT instalados en los apiarios para monitoreo. | X40: Versión | Y40: 1
A41: # | B41: Campo | C41: Descripción Campo | G41: Tipo Dato - PostgreSQL | K41: Tamaño | O41: Nulo | R41: PK | T41: FK | V41: UK | X41: Nota/Comentarios
A42: 1 | B42: id_sensor | C42: Identificador unico del sensor | G42: SERIAL | R42: S
A43: 2 | B43: tipo_sensor | C43: Tipo del sensor del apiario | G43: VARCHAR | K43: 50 | O43: NO
A44: 3 | B44: id_apiario | C44: Identificador del apiario | G44: INT | O44: NO | T44: S
A45: 4 | B45: fecha_instalacion | C45: Fechs de la instalacion del sensor | G45: DATE | O45: NO
A47: ='Invetario de Tablas'!A9 -> 6 | B47: Tabla | C47: ='Invetario de Tablas'!B9 -> lectura_sensor | G47: Descripción Tabla | K47: ='Invetario de Tablas'!C9 -> Registra los datos capturados por los sensores IoT en diferentes momentos. | X47: Versión | Y47: 1
A48: # | B48: Campo | C48: Descripción Campo | G48: Tipo Dato - PostgreSQL | K48: Tamaño | O48: Nulo | R48: PK | T48: FK | V48: UK | X48: Nota/Comentarios
A49: 1 | B49: id_lectura | C49: Identificador unico de la lectura hecha | G49: SERIAL | R49: S
A50: 2 | B50: id_sensor | C50: Identificador del sensor que hizo la lectura | G50: INT | O50: NO | T50: S
A51: 3 | B51: valor | C51: Dato principal de la medicion del sensor | G51: DECIMAL | K51: 10.2 | O51: NO
A52: 4 | B52: detalles | C52: Almacena los metadatos adicionales del sensor | G52: JSONB
A53: 5 | B53: fecha | C53: Fecha de la lectura | G53: TIMESTAMP
A55: ='Invetario de Tablas'!A10 -> 7 | B55: Tabla | C55: ='Invetario de Tablas'!B10 -> control | G55: Descripción Tabla | K55: ='Invetario de Tablas'!C10 -> Guarda el historial de revisiones sanitarias de las colmenas. | X55: Versión | Y55: 1
A56: # | B56: Campo | C56: Descripción Campo | G56: Tipo Dato - PostgreSQL | K56: Tamaño | O56: Nulo | R56: PK | T56: FK | V56: UK | X56: Nota/Comentarios
A57: 1 | B57: id_control | C57: Identificador unico del control sanitario | G57: SERIAL | R57: S
A58: 2 | B58: id_colmena | C58: Identificador de la colmena | G58: INT | O58: NO | T58: S | X58: colmena a la cual se la hace el control
A59: 3 | B59: fecha | C59: Fecha del control sanitario | G59: DATE | O59: NO
A60: 4 | B60: tratamiento | C60: Tratamiento requerido | G60: VARCHAR | K60: 150
A61: 5 | B61: observacion | C61: Observaciones luego del control | G61: TEXT
A63: ='Invetario de Tablas'!A11 -> 8 | B63: Tabla | C63: ='Invetario de Tablas'!B11 -> cosecha | G63: Descripción Tabla | K63: ='Invetario de Tablas'!C11 -> Registra las cosechas realizadas en los apiarios. | X63: Versión | Y63: 1
A64: # | B64: Campo | C64: Descripción Campo | G64: Tipo Dato - PostgreSQL | K64: Tamaño | O64: Nulo | R64: PK | T64: FK | V64: UK | X64: Nota/Comentarios
A65: 1 | B65: id_cosecha | C65: Idenificador unico de la cosecha | G65: SERIAL | R65: S
A66: 2 | B66: id_apiario | C66: Identificador del apiario | G66: INT | O66: NO | T66: S
A67: 3 | B67: fecha_cosecha | C67: Fecha de la cosecha | G67: DATE | O67: NO
A68: 4 | B68: cantidad_total | C68: Cantidad recolectada en la cosecha | G68: DECIMAL | K68: 10.2 | O68: NO
A70: ='Invetario de Tablas'!A12 -> 9 | B70: Tabla | C70: ='Invetario de Tablas'!B12 -> lote | G70: Descripción Tabla | K70: ='Invetario de Tablas'!C12 -> Registra los lotes de productos apícolas derivados de una cosecha específica. | X70: Versión | Y70: 1
A71: ='Invetario de Tablas'!A12 -> 9 | B71: Campo | C71: Descripción Campo | G71: Tipo Dato - PostgreSQL | K71: Tamaño | O71: Nulo | R71: PK | T71: FK | V71: UK | X71: Nota/Comentarios
A72: 1 | B72: id_lote | C72: Identificador unico del lote | G72: SERIAL | R72: S
A73: 2 | B73: id_cosecha | C73: Identificador de la cosecha | G73: INT | O73: NO | T73: S
A74: 3 | B74: tipo_producto | C74: Tipo de producto del lote | G74: VARCHAR | K74: 50 | O74: NO
A75: 4 | B75: cantidad_producida | C75: Cantidad producida para el lote | G75: DECIMAL | K75: 10.2 | R75: NO
A77: ='Invetario de Tablas'!A13 -> 10 | B77: Tabla | C77: ='Invetario de Tablas'!B13 -> inventario | G77: Descripción Tabla | K77: ='Invetario de Tablas'!C13 -> Registra el control de existencias de los lotes de productos apícolas. | X77: Versión | Y77: 1
A78: # | B78: Campo | C78: Descripción Campo | G78: Tipo Dato - PostgreSQL | K78: Tamaño | O78: Nulo | R78: PK | T78: FK | V78: UK | X78: Nota/Comentarios
A79: 1 | B79: id_inventario | C79: Identificador del inventario | G79: SERIAL | R79: S
A80: 2 | B80: id_lote | C80: Identificador del lote | G80: INT | O80: NO | T80: S
A81: 3 | B81: id_usuario | C81: Identificador del ususario | G81: INT | O81: NO | T81: S
A82: 4 | B82: cantidad_disponible | C82: Cantidad disponible | G82: DECIMAL | K82: 10.2 | O82: NO
A84: ='Invetario de Tablas'!A14 -> 11 | B84: Tabla | C84: ='Invetario de Tablas'!B14 -> publicacion | G84: Descripción Tabla | K84: invetario de Tablas | X84: Versión | Y84: 1
A85: # | B85: Campo | C85: Descripción Campo | G85: Tipo Dato - PostgreSQL | K85: Tamaño | O85: Nulo | R85: PK | T85: FK | V85: UK | X85: Nota/Comentarios
A86: 1 | B86: id_publicacion | C86: Identificador de la publicacion | G86: SERIAL | R86: S
A87: 2 | B87: id_lote | C87: Identificador del lote de la publicacion | G87: INT | O87: NO | T87: S
A88: 3 | B88: id_usuario | C88: Identificador del usuario de la publicacion | G88: INT | O88: NO | T88: S
A89: 4 | B89: precio | C89: Precio del producto de la publicacion | G89: DECIMAL | K89: 10.2 | O89: NO
A90: 5 | B90: estado | C90: Estado del producto en la publicacion | G90: VARCAHR | K90: 50 | O90: NO | X90: Tiene un CHECK disponible, vendido o pausado
A91: 6 | B91: fecha_publicacion | C91: Fecha de la publicacion | G91: DATE | O91: NO
A93: ='Invetario de Tablas'!A15 -> 12 | B93: Tabla | C93: ='Invetario de Tablas'!B15 -> pedido | G93: Descripción Tabla | K93: ='Invetario de Tablas'!C15 -> Almacena los pedidos realizados por consumidores o cooperativas. | X93: Versión | Y93: 1
A94: # | B94: Campo | C94: Descripción Campo | G94: Tipo Dato - PostgreSQL | K94: Tamaño | O94: Nulo | R94: PK | T94: FK | V94: UK | X94: Nota/Comentarios
A95: 1 | B95: id_pedido | C95: Identificador del pedido | G95: SERIAL | R95: S
A96: 2 | B96: id_usuario | C96: Identificador del usuario del pedido | G96: INT | O96: NO | T96: S
A97: 3 | B97: fecha_pedido | C97: Fecha de cuando se hizo el pedido | G97: DATE | O97: NO
A98: 4 | B98: estado | C98: Estado en el que se encuentra el pedido | G98: VARCHAR | K98: 50 | O98: NO | X98: Tiene un CHECK pendiente, pagado, enviado, cancelado
A100: ='Invetario de Tablas'!A16 -> 13 | B100: Tabla | C100: ='Invetario de Tablas'!B16 -> pedido_lote | G100: Descripción Tabla | K100: ='Invetario de Tablas'!C16 -> Tabla intermedia M:N que relaciona pedidos con los lotes incluidos. | X100: Versión
A101: # | B101: Campo | C101: Descripción Campo | G101: Tipo Dato - PostgreSQL | K101: Tamaño | O101: Nulo | R101: PK | T101: FK | V101: UK | X101: Nota/Comentarios
A102: 1 | B102: id_pedido | C102: Identificador del pedido | G102: INT | O102: NO | T102: S
A103: 2 | B103: id_lote | C103: Identificador del lote | G103: INT | O103: NO | T103: S
A104: 3 | B104: cantidad | C104: Cantidad específica de producto vinculada del lote al pedido. | G104: DECIMAL | K104: 10.2 | O104: NO | X104: CHECK para que sea mayor a 0
A106: ='Invetario de Tablas'!A17 -> 14 | B106: Tabla | C106: ='Invetario de Tablas'!B17 -> pago | G106: Descripción Tabla | K106: ='Invetario de Tablas'!C17 -> Registra los pagos realizados por los pedidos en la plataforma. | X106: Versión
A107: # | B107: Campo | C107: Descripción Campo | G107: Tipo Dato - PostgreSQL | K107: Tamaño | O107: Nulo | R107: PK | T107: FK | V107: UK | X107: Nota/Comentarios
A108: 1 | B108: id_pago | C108: Identificador del pago | G108: SERIAL | R108: S
A109: 2 | B109: id_pedido | C109: Identificador del pedido al que se le hace pago | G109: INT | O109: NO | T109: S
A110: 3 | B110: monto | C110: Monto/cantidad del pago | G110: DECIMAL | K110: 10.2 | O110: NO | X110: CHECK para que sea mayor a 0
A111: 4 | B111: metodo_pago | C111: Metodo del pago | G111: VARCAHAR | K111: 50 | O111: NO
A112: 5 | B112: estado_pago | C112: Estado en el que se encuentra el pago | G112: VARCAHAR | K112: 30 | O112: NO | X112: CHECK pendiente, pagado, o rechazado
A113: 6 | B113: fecha_pago | C113: Fecha en la que se hizo el pago | G113: DATE | O113: NO
A115: ='Invetario de Tablas'!A18 -> 15 | B115: Tabla | C115: ='Invetario de Tablas'!B18 -> envio | G115: Descripción Tabla | K115: ='Invetario de Tablas'!C18 -> Gestiona la información de envío y trazabilidad logística de los pedidos. | X115: Versión
...

Sheet Diccionario Datos - MySQL
A1: MySQL - Tablas en Detalle
A3: 1 | B3: Tabla | C3: organizacion | G3: Descripción Tabla | K3: Contiene los datos de cooperativas, asociaciones apícolas o entidades relacionadas con el sector. | X3: Versión
A4: # | B4: Campo | C4: Descripción Campo | G4: Tipo Dato - MySQL | K4: Tamaño | O4: Nulo | R4: PK | T4: FK | V4: UK | X4: Nota/Comentarios
A5: 1 | B5: id_organizacion | C5: Identificador unico de las organizaciones | G5: INT AUTO_INCREMENT | R5: S
A6: 2 | B6: nombre | C6: Nombre de la organizacion | G6: VARCHAR | K6: 100 | O6: NO
A7: 3 | B7: tipo | C7: Tipo de la organizacion | G7: VARCHAR | K7: 50 | O7: NO
A8: 4 | B8: direccion | C8: Direccion de la organizacion | G8: VARCHAR | K8: 150
A9: 5 | B9: telefono | C9: Telefono de contacto de la organizacion | G9: VARCHAR | K9: 25
A10: 6 | B10: nit | C10: Numero de identificacion tributaria | G10: VARCHAR | K10: 20 | O10: NO | V10: S
A12: 2 | B12: Tabla | C12: usuarios | G12: Descripción Tabla | K12: Almacena la información de las personas registradas en la plataforma como productores, consumidores, administradores o entidades regulatorias. | X12: Versión
A13: # | B13: Campo | C13: Descripción Campo | G13: Tipo Dato - MySQL | K13: Tamaño | O13: Nulo | R13: PK | T13: FK | V13: UK | X13: Nota/Comentarios
A14: 1 | B14: id_usuario | C14: Identificador unico del usuario | G14: INT AUTO_INCREMENT | R14: S
A15: 2 | B15: nombre | C15: Nombre del usuario | G15: VARCHAR | K15: 100 | O15: NO
A16: 3 | B16: email | C16: Correo electronico del usuario | G16: VARCHAR | K16: 130 | O16: NO | V16: S
A17: 4 | B17: contrasena | C17: Contrasena del usuario | G17: VARCHAR | K17: 260 | O17: NO | X17: Se omite 'n~' por buenas practicas y compatibilidad de codificacion en BD.
A18: 5 | B18: telefono | C18: Telefono de contacto | G18: VARCHAR | K18: 25
A19: 6 | B19: tipo_usuario | C19: Rol del usuario | G19: VARCHAR | K19: 30 | O19: NO | X19: Rol del usuario: productor, consumidor o administrador
A20: 7 | B20: fecha_registro | C20: Fecha del registro | G20: DATE | O20: NO
A21: 8 | B21: id_organizacion | C21: Identificador de la organizacion a la que pertenece | G21: INT | O21: NO | T21: S | X21: Referencia a la tabla organizacion
A22: N
A23: 3 | B23: Tabla | C23: apiario | G23: Descripción Tabla | K23: Registra los apiarios donde se encuentran las colmenas, incluyendo ubicación geográfica y productor responsable. | X23: Versión
A24: # | B24: Campo | C24: Descripción Campo | G24: Tipo Dato - MySQL | K24: Tamaño | O24: Nulo | R24: PK | T24: FK | V24: UK | X24: Nota/Comentarios
A25: 1 | B25: id_apiario | C25: Identificador unico del apiario | G25: INT AUTO_INCREMENT | R25: S
A26: 2 | B26: nombre_apiario | C26: Nombre del apiario | G26: VARCHAR | K26: 100 | O26: NO
A27: 3 | B27: ubicacion | C27: Ubicacion del apiario | G27: JSON | O27: NO | X27: Equivalente al JSONB de PostgreSQL en MySQL
A28: 4 | B28: id_usuario | C28: Identificador unico del usuario | G28: INT | O28: NO | T28: S
A29: 5 | B29: descripcion | C29: Descripcion de apiario | G29: TEXT
A31: 4 | B31: Tabla | C31: colmena | G31: Descripción Tabla | K31: Almacena información individual de cada colmena dentro de un apiario. | X31: Versión
A32: # | B32: Campo | C32: Descripción Campo | G32: Tipo Dato - MySQL | K32: Tamaño | O32: Nulo | R32: PK | T32: FK | V32: UK | X32: Nota/Comentarios
A33: 1 | B33: id_colmena | C33: Identificador unico de la colmena | G33: INT AUTO_INCREMENT | R33: S
A34: 2 | B34: id_apiario | C34: Identificador del apiario | G34: INT | O34: NO | T34: S
A35: 3 | B35: codigo_colmena | C35: Identificador fisico de la colmena | G35: VARCHAR | K35: 50 | O35: NO | V35: S
A36: 4 | B36: estado | C36: Estado en el que se encuentra la colmena | G36: VARCHAR | K36: 50 | O36: NO
A37: 5 | B37: tipo_abeja | C37: Tipo de abeja de la colmena | G37: VARCHAR | K37: 50 | O37: NO
A38: 6 | B38: fecha_instalacion | C38: Fecha de instalacion de la colmena | G38: DATE | O38: NO
A40: 5 | B40: Tabla | C40: sensor | G40: Descripción Tabla | K40: Contiene la información de los sensores IoT instalados en los apiarios para monitoreo. | X40: Versión
A41: # | B41: Campo | C41: Descripción Campo | G41: Tipo Dato - MySQL | K41: Tamaño | O41: Nulo | R41: PK | T41: FK | V41: UK | X41: Nota/Comentarios
A42: 1 | B42: id_sensor | C42: Identificador unico del sensor | G42: INT AUTO_INCREMENT | R42: S
A43: 2 | B43: tipo_sensor | C43: Tipo del sensor del apiario | G43: VARCHAR | K43: 50 | O43: NO
A44: 3 | B44: id_apiario | C44: Identificador del apiario | G44: INT | O44: NO | T44: S
A45: 4 | B45: fecha_instalacion | C45: Fecha de la instalacion del sensor | G45: DATE | O45: NO
A47: 6 | B47: Tabla | C47: lectura_sensor | G47: Descripción Tabla | K47: Registra los datos capturados por los sensores IoT en diferentes momentos. | X47: Versión
A48: # | B48: Campo | C48: Descripción Campo | G48: Tipo Dato - MySQL | K48: Tamaño | O48: Nulo | R48: PK | T48: FK | V48: UK | X48: Nota/Comentarios
A49: 1 | B49: id_lectura | C49: Identificador unico de la lectura hecha | G49: INT AUTO_INCREMENT | R49: S
A50: 2 | B50: id_sensor | C50: Identificador del sensor que hizo la lectura | G50: INT | O50: NO | T50: S
A51: 3 | B51: valor | C51: Dato principal de la medicion del sensor | G51: DECIMAL(10,2) | O51: NO
A52: 4 | B52: detalles | C52: Almacena los metadatos adicionales del sensor | G52: JSON | X52: JSON equivalente al JSONB de PostgreSQL
A53: 5 | B53: fecha | C53: Fecha de la lectura | G53: DATETIME
A55: 7 | B55: Tabla | C55: control | G55: Descripción Tabla | K55: Guarda el historial de revisiones sanitarias de las colmenas. | X55: Versión
A56: # | B56: Campo | C56: Descripción Campo | G56: Tipo Dato - MySQL | K56: Tamaño | O56: Nulo | R56: PK | T56: FK | V56: UK | X56: Nota/Comentarios
A57: 1 | B57: id_control | C57: Identificador unico del control sanitario | G57: INT AUTO_INCREMENT | R57: S
A58: 2 | B58: id_colmena | C58: Identificador de la colmena | G58: INT | O58: NO | T58: S | X58: Colmena a la cual se le hace el control
A59: 3 | B59: fecha | C59: Fecha del control sanitario | G59: DATE | O59: NO
A60: 4 | B60: tratamiento | C60: Tratamiento requerido | G60: VARCHAR | K60: 150
A61: 5 | B61: observacion | C61: Observaciones luego del control | G61: TEXT
A63: 8 | B63: Tabla | C63: cosecha | G63: Descripción Tabla | K63: Registra las cosechas realizadas en los apiarios. | X63: Versión
A64: # | B64: Campo | C64: Descripción Campo | G64: Tipo Dato - MySQL | K64: Tamaño | O64: Nulo | R64: PK | T64: FK | V64: UK | X64: Nota/Comentarios
A65: 1 | B65: id_cosecha | C65: Identificador unico de la cosecha | G65: INT AUTO_INCREMENT | R65: S
A66: 2 | B66: id_apiario | C66: Identificador del apiario | G66: INT | O66: NO | T66: S
A67: 3 | B67: fecha_cosecha | C67: Fecha de la cosecha | G67: DATE | O67: NO
A68: 4 | B68: cantidad_total | C68: Cantidad recolectada en la cosecha | G68: DECIMAL(10,2) | O68: NO
A70: 9 | B70: Tabla | C70: lote | G70: Descripción Tabla | K70: Registra los lotes de productos apícolas derivados de una cosecha específica. | X70: Versión
A71: # | B71: Campo | C71: Descripción Campo | G71: Tipo Dato - MySQL | K71: Tamaño | O71: Nulo | R71: PK | T71: FK | V71: UK | X71: Nota/Comentarios
A72: 1 | B72: id_lote | C72: Identificador unico del lote | G72: INT AUTO_INCREMENT | R72: S
A73: 2 | B73: id_cosecha | C73: Identificador de la cosecha | G73: INT | O73: NO | T73: S
A74: 3 | B74: tipo_producto | C74: Tipo de producto del lote | G74: VARCHAR | K74: 50 | O74: NO
A75: 4 | B75: cantidad_producida | C75: Cantidad producida para el lote | G75: DECIMAL(10,2) | O75: NO
A77: 10 | B77: Tabla | C77: inventario | G77: Descripción Tabla | K77: Registra el control de existencias de los lotes de productos apícolas. | X77: Versión
A78: # | B78: Campo | C78: Descripción Campo | G78: Tipo Dato - MySQL | K78: Tamaño | O78: Nulo | R78: PK | T78: FK | V78: UK | X78: Nota/Comentarios
A79: 1 | B79: id_inventario | C79: Identificador del inventario | G79: INT AUTO_INCREMENT | R79: S
A80: 2 | B80: id_lote | C80: Identificador del lote | G80: INT | O80: NO | T80: S
A81: 3 | B81: id_usuario | C81: Identificador del usuario | G81: INT | O81: NO | T81: S
A82: 4 | B82: cantidad_disponible | C82: Cantidad disponible | G82: DECIMAL(10,2) | O82: NO
A84: 11 | B84: Tabla | C84: publicacion | G84: Descripción Tabla | K84: Permite a los productores publicar lotes disponibles para venta en el marketplace. | X84: Versión
A85: # | B85: Campo | C85: Descripción Campo | G85: Tipo Dato - MySQL | K85: Tamaño | O85: Nulo | R85: PK | T85: FK | V85: UK | X85: Nota/Comentarios
A86: 1 | B86: id_publicacion | C86: Identificador de la publicacion | G86: INT AUTO_INCREMENT | R86: S
A87: 2 | B87: id_lote | C87: Identificador del lote de la publicacion | G87: INT | O87: NO | T87: S
A88: 3 | B88: id_usuario | C88: Identificador del usuario de la publicacion | G88: INT | O88: NO | T88: S
A89: 4 | B89: precio | C89: Precio del producto de la publicacion | G89: DECIMAL(10,2) | O89: NO
A90: 5 | B90: estado | C90: Estado del producto en la publicacion | G90: ENUM('disponible','vendido','pausado') | O90: NO | X90: CHECK: disponible, vendido o pausado
A91: 6 | B91: fecha_publicacion | C91: Fecha de la publicacion | G91: DATE | O91: NO
A93: 12 | B93: Tabla | C93: pedido | G93: Descripción Tabla | K93: Almacena los pedidos realizados por consumidores o cooperativas. | X93: Versión
A94: # | B94: Campo | C94: Descripción Campo | G94: Tipo Dato - MySQL | K94: Tamaño | O94: Nulo | R94: PK | T94: FK | V94: UK | X94: Nota/Comentarios
A95: 1 | B95: id_pedido | C95: Identificador del pedido | G95: INT AUTO_INCREMENT | R95: S
A96: 2 | B96: id_usuario | C96: Identificador del usuario del pedido | G96: INT | O96: NO | T96: S
A97: 3 | B97: fecha_pedido | C97: Fecha de cuando se hizo el pedido | G97: DATE | O97: NO
A98: 4 | B98: estado | C98: Estado en el que se encuentra el pedido | G98: ENUM('pendiente','pagado','enviado','cancelado') | O98: NO | X98: CHECK: pendiente, pagado, enviado, cancelado
A99: N
A101: 13 | B101: Tabla | C101: pedido_lote | G101: Descripción Tabla | K101: Tabla intermedia M:N que relaciona pedidos con los lotes incluidos. | X101: Versión
A102: # | B102: Campo | C102: Descripción Campo | G102: Tipo Dato - MySQL | K102: Tamaño | O102: Nulo | R102: PK | T102: FK | V102: UK | X102: Nota/Comentarios
A103: 1 | B103: id_pedido | C103: Identificador del pedido | G103: INT | O103: NO | T103: S
A104: 2 | B104: id_lote | C104: Identificador del lote | G104: INT | O104: NO | T104: S
A105: 3 | B105: cantidad | C105: Cantidad especifica de producto vinculada del lote al pedido | G105: DECIMAL(10,2) | O105: NO | X105: CHECK para que sea mayor a 0
A106: N
A108: 14 | B108: Tabla | C108: pago | G108: Descripción Tabla | K108: Registra los pagos realizados por los pedidos en la plataforma. | X108: Versión
A109: # | B109: Campo | C109: Descripción Campo | G109: Tipo Dato - MySQL | K109: Tamaño | O109: Nulo | R109: PK | T109: FK | V109: UK | X109: Nota/Comentarios
A110: 1 | B110: id_pago | C110: Identificador del pago | G110: INT AUTO_INCREMENT | R110: S
A111: 2 | B111: id_pedido | C111: Identificador del pedido al que se le hace pago | G111: INT | O111: NO | T111: S
A112: 3 | B112: monto | C112: Monto del pago | G112: DECIMAL(10,2) | O112: NO | X112: CHECK para que sea mayor a 0
A113: 4 | B113: metodo_pago | C113: Metodo del pago | G113: VARCHAR | K113: 50 | O113: NO
...

Sheet Diccionario Datos - MS SQL Serv
A1: MS SQL Server - Tablas en Detalle
A3: 1 | B3: Tabla | C3: organizacion | G3: Descripción Tabla | K3: Contiene los datos de cooperativas, asociaciones apícolas o entidades relacionadas con el sector. | X3: Versión | Y3: 1
A4: # | B4: Campo | C4: Descripción Campo | G4: Tipo Dato - MSSQLSERVER | K4: Tamaño | O4: Nulo | R4: PK | T4: FK | V4: UK | X4: Nota/Comentarios
A5: 1 | B5: id_organizacion | C5: Identificador unico de las organizaciones | G5: INT IDENTITY(1,1) | K5: 4 | O5: NO | R5: S | X5: Clave primaria autoincremental
A6: 2 | B6: nombre | C6: Nombre de la organizacion | G6: VARCHAR | K6: 100 | O6: NO
A7: 3 | B7: tipo | C7: Tipo de la organizacion | G7: VARCHAR | K7: 50 | O7: NO
A8: 4 | B8: direccion | C8: direccion de la organizacion | G8: VARCHAR | K8: 150 | O8: SI
A9: 5 | B9: telefono | C9: Telefono de contacto de la organizacion | G9: VARCHAR | K9: 25 | O9: SI
A10: 6 | B10: nit | C10: Numero de identificacion tributaria | G10: VARCHAR | K10: 20 | O10: NO | V10: S | X10: Valor único
A12: 2 | B12: Tabla | C12: usuarios | G12: Descripción Tabla | K12: Almacena la información de las personas registradas en la plataforma como productores, consumidores, administradores o entidades regulatorias. | X12: Versión | Y12: 1
A13: # | B13: Campo | C13: Descripción Campo | G13: Tipo Dato - MSSQLSERVER | K13: Tamaño | O13: Nulo | R13: PK | T13: FK | V13: UK | X13: Nota/Comentarios
A14: 1 | B14: id_usuario | C14: identificador unico del usuario | G14: INT IDENTITY(1,1) | O14: NO | R14: S | X14: Clave primaria autoincremental
A15: 2 | B15: nombre | C15: Nombre del usuario | G15: VARCHAR | K15: 100 | O15: NO
A16: 3 | B16: email | C16: Correo electronico del usuario | G16: VARCHAR | K16: 130 | O16: NO | V16: S
A17: 4 | B17: contrasena | C17: Contraseña del usuario | G17: VARCHAR | K17: 260 | O17: NO | X17: Valor único
A18: 5 | B18: telefono | C18: Telefono de contacto | G18: VARCHAR | K18: 25 | O18: SI | X18: Almacenar con hash
A19: 6 | B19: tipo_usuario | C19: Rol del usuario | G19: VARCHAR | K19: 30 | O19: NO | X19: Rol del usuario ej. productor, consumidor, o administrador
A20: 7 | B20: fecha_registro | C20: Fecha del registro | G20: DATE | O20: NO | X20: Default: fecha actual
A21: 8 | B21: id_organizacion | C21: identificador de la organiazicion a la que pertenece | G21: INT | O21: SI | T21: S | X21: Referencia a la tabla organizacion
A23: 3 | B23: Tabla | C23: apiario | G23: Descripción Tabla | K23: ='Invetario de Tablas'!C6 -> Registra los apiarios donde se encuentran las colmenas, incluyendo ubicación geográfica y productor responsable. | X23: Versión | Y23: 1
A24: # | B24: Campo | C24: Descripción Campo | G24: Tipo Dato - MSSQLSERVER | K24: Tamaño | O24: Nulo | R24: PK | T24: FK | V24: UK | X24: Nota/Comentarios
A25: 1 | B25: id_apiario | C25: Identificador unico del apiario | G25: INT IDENTITY(1,1) | O25: NO | R25: S | X25: Clave primaria autoincremental
A26: 2 | B26: nombre_apiario | C26: Nombre del apiario | G26: VARCHAR(100) | K26: 100 | O26: NO
A27: 3 | B27: ubicacion | C27: Ubicacion del apiario | G27: NVARCHAR | K27: MAX | O27: NO | X27: Se definio como jsonb
A28: 4 | B28: id_usuario | C28: Identificador unico del usuario | G28: INT | O28: NO | T28: S
A29: 5 | B29: descripcion | C29: Descripcion de apiario | G29: VARCHAR(100) | K29: MAX | O29: SI
A31: 4 | B31: Tabla | C31: colmena | G31: Descripción Tabla | K31: ='Invetario de Tablas'!C7 -> Almacena información individual de cada colmena dentro de un apiario. | X31: Versión | Y31: 1
A32: # | B32: Campo | C32: Descripción Campo | G32: Tipo Dato - MSSQLSERVER | K32: Tamaño | O32: Nulo | R32: PK | T32: FK | V32: UK | X32: Nota/Comentarios
A33: 1 | B33: id_colmena | C33: Identificador unico de la colmena | G33: INT IDENTITY(1,1) | O33: NO | R33: S
A34: 2 | B34: id_apiario | C34: Identificador del apiario | G34: INT IDENTITY(1,1) | O34: NO | T34: S
A35: 3 | B35: codigo_colmena | C35: Identificador fisico del apiario | G35: VARCHAR(30) | K35: 30 | O35: NO | V35: S
A36: 4 | B36: estado | C36: Estado en el que se encuentra la colmena | G36: VARCHAR(50) | K36: 50 | O36: NO
A37: 5 | B37: tipo_abeja | C37: Tipo de abeja de la colmena | G37: VARCHAR(50) | K37: 50 | O37: NO
A38: 6 | B38: fecha_instalacion | C38: Fecha de instalacion de la colmena | G38: DATETIME2 | O38: NO
A40: 5 | B40: Tabla | C40: sensor | G40: Descripción Tabla | K40: ='Invetario de Tablas'!C8 -> Contiene la información de los sensores IoT instalados en los apiarios para monitoreo. | X40: Versión | Y40: 1
A41: # | B41: Campo | C41: Descripción Campo | G41: Tipo Dato - MSSQLSERVER | K41: Tamaño | O41: Nulo | R41: PK | T41: FK | V41: UK | X41: Nota/Comentarios
A42: 1 | B42: id_sensor | C42: Identificador unico del sensor | G42: INT IDENTITY(1,1) | R42: S
A43: 2 | B43: tipo_sensor | C43: Tipo del sensor del apiario | G43: VARCHAR | K43: 50 | O43: NO
A44: 3 | B44: id_apiario | C44: Identificador del apiario | G44: INT | O44: NO | T44: S
A45: 4 | B45: fecha_instalacion | C45: Fechs de la instalacion del sensor | G45: DATE | O45: NO
A47: 6 | B47: Tabla | C47: lectura_sensor | G47: Descripción Tabla | K47: ='Invetario de Tablas'!C9 -> Registra los datos capturados por los sensores IoT en diferentes momentos. | X47: Versión | Y47: 1
A48: # | B48: Campo | C48: Descripción Campo | G48: Tipo Dato - MSSQLSERVER | K48: Tamaño | O48: Nulo | R48: PK | T48: FK | V48: UK | X48: Nota/Comentarios
A49: 1 | B49: id_lectura | C49: Identificador unico de la lectura hecha | G49: INT IDENTITY(1,1) | O49: NO | R49: S
A50: 2 | B50: id_sensor | C50: Identificador del sensor que hizo la lectura | G50: INT | O50: NO | T50: S
A51: 3 | B51: valor | C51: Dato principal de la medicion del sensor | G51: DECIMAL | K51: 10.2 | O51: NO
A52: 4 | B52: detalles | C52: Almacena los metadatos adicionales del sensor | G52: NVARCHAR | K52: MAX | O52: NO
A53: 5 | B53: fecha | C53: Fecha de la lectura | G53: DATE | O53: NO
A55: 7 | B55: Tabla | C55: control | G55: Descripción Tabla | K55: ='Invetario de Tablas'!C10 -> Guarda el historial de revisiones sanitarias de las colmenas. | X55: Versión | Y55: 1
A56: # | B56: Campo | C56: Descripción Campo | G56: Tipo Dato - MSSQLSERVER | K56: Tamaño | O56: Nulo | R56: PK | T56: FK | V56: UK | X56: Nota/Comentarios
A57: 1 | B57: id_control | C57: Identificador unico del control sanitario | G57: INT IDENTITY(1,1) | R57: S
A58: 2 | B58: id_colmena | C58: Identificador de la colmena | G58: INT | O58: NO | T58: S | X58: colmena a la cual se la hace el control
A59: 3 | B59: fecha | C59: Fecha del control sanitario | G59: DATETIME2 | O59: NO
A60: 4 | B60: tratamiento | C60: Tratamiento requerido | G60: VARCHAR | K60: 150
A61: 5 | B61: observacion | C61: Observaciones luego del control | G61: VARCHAR | K61: MAX
A63: 8 | B63: Tabla | C63: cosecha | G63: Descripción Tabla | K63: ='Invetario de Tablas'!C11 -> Registra las cosechas realizadas en los apiarios. | X63: Versión | Y63: 1
A64: # | B64: Campo | C64: Descripción Campo | G64: Tipo Dato - MSSQLSERVER | K64: Tamaño | O64: Nulo | R64: PK | T64: FK | V64: UK | X64: Nota/Comentarios
A65: 1 | B65: id_cosecha | C65: Idenificador unico de la cosecha | G65: INT | R65: S
A66: 2 | B66: id_apiario | C66: Identificador del apiario | G66: INT | O66: NO | T66: S
A67: 3 | B67: fecha_cosecha | C67: Fecha de la cosecha | G67: DATETIME2 | O67: NO
A68: 4 | B68: cantidad_total | C68: Cantidad recolectada en la cosecha | G68: DECIMAL | K68: 10.2 | O68: NO
A70: 9 | B70: Tabla | C70: lote | G70: Descripción Tabla | K70: ='Invetario de Tablas'!C12 -> Registra los lotes de productos apícolas derivados de una cosecha específica. | X70: Versión | Y70: 1
A71: 0 | B71: Campo | C71: Descripción Campo | G71: Tipo Dato - MSSQLSERVER | K71: Tamaño | O71: Nulo | R71: PK | T71: FK | V71: UK | X71: Nota/Comentarios
A72: 1 | B72: id_lote | C72: Identificador unico del lote | G72: INT IDENTITY(1,1) | R72: S
A73: 2 | B73: id_cosecha | C73: Identificador de la cosecha | G73: INT | O73: NO | T73: S
A74: 3 | B74: tipo_producto | C74: Tipo de producto del lote | G74: VARCHAR | K74: 50 | O74: NO
A75: 4 | B75: cantidad_producida | C75: Cantidad producida para el lote | G75: DECIMAL | K75: 10.2 | R75: NO
A77: 10 | B77: Tabla | C77: inventario | G77: Descripción Tabla | K77: ='Invetario de Tablas'!C13 -> Registra el control de existencias de los lotes de productos apícolas. | X77: Versión | Y77: 1
A78: # | B78: Campo | C78: Descripción Campo | G78: Tipo Dato - MSSQLSERVER | K78: Tamaño | O78: Nulo | R78: PK | T78: FK | V78: UK | X78: Nota/Comentarios
A79: 1 | B79: id_inventario | C79: Identificador del inventario | G79: INT | R79: S
A80: 2 | B80: id_lote | C80: Identificador del lote | G80: INT | O80: NO | T80: S
A81: 3 | B81: id_usuario | C81: Identificador del ususario | G81: INT | O81: NO | T81: S
A82: 4 | B82: cantidad_disponible | C82: Cantidad disponible | G82: DECIMAL | K82: 10.2 | O82: NO
A84: 11 | B84: Tabla | C84: publicacion | G84: Descripción Tabla | K84: ='Invetario de Tablas'!C14 -> Permite a los productores publicar lotes disponibles para venta en el marketplace. | X84: Versión | Y84: 1
A85: # | B85: Campo | C85: Descripción Campo | G85: Tipo Dato - MSSQLSERVER | K85: Tamaño | O85: Nulo | R85: PK | T85: FK | V85: UK | X85: Nota/Comentarios
A86: 1 | B86: id_publicacion | C86: Identificador de la publicacion | G86: INT | R86: S
A87: 2 | B87: id_lote | C87: Identificador del lote de la publicacion | G87: INT | O87: NO | T87: S
A88: 3 | B88: id_usuario | C88: Identificador del usuario de la publicacion | G88: INT | O88: NO | T88: S
A89: 4 | B89: precio | C89: Precio del producto de la publicacion | G89: DECIMAL | K89: 10.2 | O89: NO
A90: 5 | B90: estado | C90: Estado del producto en la publicacion | G90: VARCAHR | K90: 30 | O90: NO | X90: Tiene un CHECK disponible, vendido o pausado
A91: 6 | B91: fecha_publicacion | C91: Fecha de la publicacion | G91: DATETIME2 | O91: NO
A93: 12 | B93: Tabla | C93: pedido | G93: Descripción Tabla | K93: ='Invetario de Tablas'!C15 -> Almacena los pedidos realizados por consumidores o cooperativas. | X93: Versión | Y93: 1
A94: # | B94: Campo | C94: Descripción Campo | G94: Tipo Dato - MSSQLSERVER | K94: Tamaño | O94: Nulo | R94: PK | T94: FK | V94: UK | X94: Nota/Comentarios
A95: 1 | B95: id_pedido | C95: Identificador del pedido | G95: INT IDENTITY(1,1) | R95: S
A96: 2 | B96: id_usuario | C96: Identificador del usuario del pedido | G96: INT | O96: NO | T96: S
A97: 3 | B97: fecha_pedido | C97: Fecha de cuando se hizo el pedido | G97: DATETIME2 | O97: NO
A98: 4 | B98: estado | C98: Estado en el que se encuentra el pedido | G98: VARCHAR | K98: 50 | O98: NO | X98: Tiene un CHECK pendiente, pagado, enviado, cancelado
A100: 12 | B100: Tabla | C100: pedido_lote | G100: Descripción Tabla | K100: ='Invetario de Tablas'!C16 -> Tabla intermedia M:N que relaciona pedidos con los lotes incluidos. | X100: Versión
A101: # | B101: Campo | C101: Descripción Campo | G101: Tipo Dato - MSSQLSERVER | K101: Tamaño | O101: Nulo | R101: PK | T101: FK | V101: UK | X101: Nota/Comentarios
A102: 1 | B102: id_pedido | C102: Identificador del pedido | G102: INT | O102: NO | T102: S
A103: 2 | B103: id_lote | C103: Identificador del lote | G103: INT | O103: NO | T103: S
A104: 3 | B104: cantidad | C104: Cantidad específica de producto vinculada del lote al pedido. | G104: DECIMAL | K104: 10.2 | O104: NO | X104: CHECK para que sea mayor a 0
A106: 13 | B106: Tabla | C106: pago | G106: Descripción Tabla | K106: ='Invetario de Tablas'!C17 -> Registra los pagos realizados por los pedidos en la plataforma. | X106: Versión
A107: # | B107: Campo | C107: Descripción Campo | G107: Tipo Dato - MSSQLSERVER | K107: Tamaño | O107: Nulo | R107: PK | T107: FK | V107: UK | X107: Nota/Comentarios
A108: 1 | B108: id_pago | C108: Identificador del pago | G108: INT IDENTITY(1,1) | R108: S
A109: 2 | B109: id_pedido | C109: Identificador del pedido al que se le hace pago | G109: INT | O109: NO | T109: S
A110: 3 | B110: monto | C110: Monto/cantidad del pago | G110: DECIMAL | K110: 10.2 | O110: NO | X110: CHECK para que sea mayor a 0
A111: 4 | B111: metodo_pago | C111: Metodo del pago | G111: VARCAHAR | K111: 50 | O111: NO
A112: 5 | B112: estado_pago | C112: Estado en el que se encuentra el pago | G112: VARCAHAR | K112: 30 | O112: NO | X112: CHECK pendiente, pagado, o rechazado
A113: 6 | B113: fecha_pago | C113: Fecha en la que se hizo el pago | G113: DATETIME2 | O113: NO
A115: 14 | B115: Tabla | C115: envio | G115: Descripción Tabla | K115: ='Invetario de Tablas'!C18 -> Gestiona la información de envío y trazabilidad logística de los pedidos. | X115: Versión
...
